mednoise/__init__.py
mednoise/all.py
mednoise/artificial.py
mednoise/branch.py
mednoise/hotspot.py
mednoise/manual.py
mednoise-1.2.4.dist-info/LICENSE
mednoise-1.2.4.dist-info/METADATA
mednoise-1.2.4.dist-info/WHEEL
mednoise-1.2.4.dist-info/top_level.txt
mednoise-1.2.4.dist-info/RECORD
