Metadata-Version: 2.1
Name: mednoise
Version: 1.2.4
Summary: mednoise is a python package that contains algorithms to handle and edit large amounts of image-based metadata to remove irrelevant noise and enhance the accuracy of machine learning and deep learning models for scientific research.
Home-page: https://github.com/mednoise/mednoise
Author: Ravi Bandaru
Author-email: ravi14.bandaru@gmail.com
License: UNKNOWN
Project-URL: Bug Tracker, https://github.com/mednoise/mednoise/issues
Platform: UNKNOWN
Classifier: Programming Language :: Python :: 3
Classifier: License :: OSI Approved :: Apache Software License
Classifier: Operating System :: OS Independent
Requires-Python: >=3.6
License-File: LICENSE
